voip_utils/__init__.py
voip_utils/const.py
voip_utils/error.py
voip_utils/pyaudioop.py
voip_utils/rtp_audio.py
voip_utils/sip.py
voip_utils/util.py
voip_utils/voip.py
voip_utils-0.3.5.dist-info/LICENSE.md
voip_utils-0.3.5.dist-info/METADATA
voip_utils-0.3.5.dist-info/WHEEL
voip_utils-0.3.5.dist-info/top_level.txt
voip_utils-0.3.5.dist-info/zip-safe
voip_utils-0.3.5.dist-info/RECORD
